deferred2/__init__.py
deferred2/batcher.py
deferred2-0.0.1.dist-info/DESCRIPTION.rst
deferred2-0.0.1.dist-info/METADATA
deferred2-0.0.1.dist-info/RECORD
deferred2-0.0.1.dist-info/WHEEL
deferred2-0.0.1.dist-info/metadata.json
deferred2-0.0.1.dist-info/top_level.txt
