Metadata-Version: 2.0
Name: deferred2
Version: 0.0.1
Summary: Successor of the deferred library shipped with Google AppEngine (GAE)
Home-page: https://github.com/kaste/deferred2
Author: herr kaste
Author-email: herr.kaste@gmail.com
License: MIT
Platform: linux
Platform: osx
Platform: win32
Classifier: Development Status :: 4 - Beta
Classifier: Intended Audience :: Developers
Classifier: License :: OSI Approved :: MIT License
Classifier: Operating System :: POSIX
Classifier: Operating System :: Microsoft :: Windows
Classifier: Operating System :: MacOS :: MacOS X
Classifier: Topic :: Utilities
Classifier: Programming Language :: Python
